Metadata-Version: 2.4
Name: imgocr
Version: 0.2.3
Summary: Image ocr tool, use ppocr onnx model.
Home-page: https://github.com/shibing624/imgocr
Author: XuMing
Author-email: xuming624@qq.com
License: Apache License 2.0
Keywords: ocr,image ocr,text recognition
Classifier: Development Status :: 5 - Production/Stable
Classifier: Intended Audience :: Developers
Classifier: Intended Audience :: Education
Classifier: Intended Audience :: Science/Research
Classifier: License :: OSI Approved :: Apache Software License
Classifier: Operating System :: OS Independent
Classifier: Programming Language :: Python :: 3
Classifier: Topic :: Scientific/Engineering :: Artificial Intelligence
Requires-Python: >=3.6.0
License-File: LICENSE
Requires-Dist: loguru
Requires-Dist: tqdm
Requires-Dist: shapely
Requires-Dist: numpy
Requires-Dist: pillow
Requires-Dist: pyclipper
Requires-Dist: requests
Requires-Dist: opencv-python-headless
Provides-Extra: onnxruntime
Requires-Dist: onnxruntime; extra == "onnxruntime"
Provides-Extra: onnxruntime-gpu
Requires-Dist: onnxruntime-gpu; extra == "onnxruntime-gpu"
Provides-Extra: serve
Requires-Dist: uvicorn[standard]; extra == "serve"
Requires-Dist: fastapi; extra == "serve"
Requires-Dist: python-multipart; extra == "serve"
Requires-Dist: pydantic; extra == "serve"
Provides-Extra: dev
Requires-Dist: albumentations; extra == "dev"
Requires-Dist: pip-tools; extra == "dev"
Requires-Dist: pytest; extra == "dev"
Requires-Dist: datasets[vision]; extra == "dev"
Dynamic: author
Dynamic: author-email
Dynamic: classifier
Dynamic: description
Dynamic: description-content-type
Dynamic: home-page
Dynamic: keywords
Dynamic: license
Dynamic: license-file
Dynamic: provides-extra
Dynamic: requires-dist
Dynamic: requires-python
Dynamic: summary
